genialn/__init__.py
genialn/genial.py
genialn-1.0.0.dist-info/licenses/LICENSE.txt
genialn-1.0.0.dist-info/METADATA
genialn-1.0.0.dist-info/WHEEL
genialn-1.0.0.dist-info/top_level.txt
genialn-1.0.0.dist-info/RECORD
